MANIFEST.in
README.md
requirements.txt
setup.cfg
setup.py
nomine/__init__.py
nomine/generate.py
nomine/random.py
nomine.egg-info/PKG-INFO
nomine.egg-info/SOURCES.txt
nomine.egg-info/dependency_links.txt
nomine.egg-info/requires.txt
nomine.egg-info/top_level.txt