Metadata-Version: 1.1
Name: nomine
Version: 0.0.1
Summary: A complete markov chain name generator
Home-page: https://github.com/eranimo/nomine
Author: Nomine
Author-email: me@kaelan.org
License: BSD
Download-URL: https://github.com/eranimo/nomine/tarball/0.0.1
Platform: UNKNOWN
Classifier: Development Status :: 3 - Alpha
Classifier: Intended Audience :: Developers
Classifier: Programming Language :: Python :: 3
